{ "columns":16,
 "image":"0x72_16x16DungeonTileset.v4.png",
 "imageheight":256,
 "imagewidth":256,
 "margin":0,
 "name":"dungeon",
 "spacing":0,
 "tilecount":256,
 "tiledversion":"1.2.0",
 "tileheight":16,
 "tiles":[
        {
         "id":0,
         "properties":[
                {
                 "name":"walup",
                 "type":"bool",
                 "value":true
                }],
         "type":"tile"
        }, 
        {
         "id":1,
         "properties":[
                {
                 "name":"walup",
                 "type":"bool",
                 "value":true
                }],
         "type":"tile"
        }, 
        {
         "id":2,
         "type":"tile"
        }, 
        {
         "id":3,
         "type":"tile"
        }, 
        {
         "id":4,
         "type":"tile"
        }, 
        {
         "id":5,
         "type":"tile"
        }, 
        {
         "id":6,
         "type":"tile"
        }, 
        {
         "id":7,
         "type":"tile"
        }, 
        {
         "id":8,
         "type":"tile"
        }, 
        {
         "id":9,
         "type":"tile"
        }, 
        {
         "id":10,
         "type":"tile"
        }, 
        {
         "id":11,
         "type":"tile"
        }, 
        {
         "id":12,
         "type":"tile"
        }, 
        {
         "id":13,
         "type":"tile"
        }, 
        {
         "id":14,
         "type":"tile"
        }, 
        {
         "id":15,
         "type":"tile"
        }, 
        {
         "id":16,
         "type":"tile"
        }, 
        {
         "id":17,
         "type":"tile"
        }, 
        {
         "id":18,
         "type":"tile"
        }, 
        {
         "id":19,
         "type":"tile"
        }, 
        {
         "id":20,
         "type":"tile"
        }, 
        {
         "id":21,
         "type":"tile"
        }, 
        {
         "id":22,
         "type":"tile"
        }, 
        {
         "id":23,
         "type":"tile"
        }, 
        {
         "id":24,
         "type":"tile"
        }, 
        {
         "id":25,
         "type":"tile"
        }, 
        {
         "id":26,
         "type":"tile"
        }, 
        {
         "id":27,
         "type":"tile"
        }, 
        {
         "id":28,
         "type":"tile"
        }, 
        {
         "id":29,
         "type":"tile"
        }, 
        {
         "id":30,
         "type":"tile"
        }, 
        {
         "id":31,
         "type":"tile"
        }, 
        {
         "id":32,
         "type":"tile"
        }, 
        {
         "id":33,
         "type":"tile"
        }, 
        {
         "id":34,
         "type":"tile"
        }, 
        {
         "id":35,
         "type":"tile"
        }, 
        {
         "id":36,
         "type":"tile"
        }, 
        {
         "id":37,
         "type":"tile"
        }, 
        {
         "id":38,
         "type":"tile"
        }, 
        {
         "id":39,
         "type":"tile"
        }, 
        {
         "id":40,
         "type":"tile"
        }, 
        {
         "id":41,
         "type":"tile"
        }, 
        {
         "id":42,
         "type":"tile"
        }, 
        {
         "id":43,
         "type":"tile"
        }, 
        {
         "id":44,
         "type":"tile"
        }, 
        {
         "id":45,
         "type":"tile"
        }, 
        {
         "id":46,
         "type":"tile"
        }, 
        {
         "id":47,
         "type":"tile"
        }, 
        {
         "id":48,
         "type":"tile"
        }, 
        {
         "id":49,
         "type":"tile"
        }, 
        {
         "id":50,
         "type":"tile"
        }, 
        {
         "id":51,
         "type":"tile"
        }, 
        {
         "id":52,
         "type":"tile"
        }, 
        {
         "id":53,
         "type":"tile"
        }, 
        {
         "id":54,
         "type":"tile"
        }, 
        {
         "id":55,
         "type":"tile"
        }, 
        {
         "id":56,
         "type":"tile"
        }, 
        {
         "id":57,
         "type":"tile"
        }, 
        {
         "id":58,
         "type":"tile"
        }, 
        {
         "id":59,
         "type":"tile"
        }, 
        {
         "id":60,
         "type":"tile"
        }, 
        {
         "id":61,
         "type":"tile"
        }, 
        {
         "id":62,
         "type":"tile"
        }, 
        {
         "id":63,
         "type":"tile"
        }, 
        {
         "id":64,
         "type":"tile"
        }, 
        {
         "id":65,
         "type":"tile"
        }, 
        {
         "id":66,
         "type":"tile"
        }, 
        {
         "id":67,
         "type":"tile"
        }, 
        {
         "id":68,
         "type":"tile"
        }, 
        {
         "id":69,
         "type":"tile"
        }, 
        {
         "id":70,
         "type":"tile"
        }, 
        {
         "id":71,
         "type":"tile"
        }, 
        {
         "id":72,
         "type":"tile"
        }, 
        {
         "id":73,
         "type":"tile"
        }, 
        {
         "id":74,
         "type":"tile"
        }, 
        {
         "id":75,
         "type":"tile"
        }, 
        {
         "id":76,
         "type":"tile"
        }, 
        {
         "id":77,
         "type":"tile"
        }, 
        {
         "id":78,
         "type":"tile"
        }, 
        {
         "id":79,
         "type":"tile"
        }, 
        {
         "id":80,
         "type":"tile"
        }, 
        {
         "id":81,
         "type":"tile"
        }, 
        {
         "id":82,
         "type":"tile"
        }, 
        {
         "id":83,
         "type":"tile"
        }, 
        {
         "id":84,
         "type":"tile"
        }, 
        {
         "id":85,
         "type":"tile"
        }, 
        {
         "id":86,
         "type":"tile"
        }, 
        {
         "id":87,
         "type":"tile"
        }, 
        {
         "id":88,
         "type":"tile"
        }, 
        {
         "id":89,
         "type":"tile"
        }, 
        {
         "id":90,
         "type":"tile"
        }, 
        {
         "id":91,
         "type":"tile"
        }, 
        {
         "id":92,
         "type":"tile"
        }, 
        {
         "id":93,
         "type":"tile"
        }, 
        {
         "id":94,
         "type":"tile"
        }, 
        {
         "id":95,
         "type":"tile"
        }, 
        {
         "id":96,
         "type":"tile"
        }, 
        {
         "id":97,
         "type":"tile"
        }, 
        {
         "id":98,
         "type":"tile"
        }, 
        {
         "id":99,
         "type":"tile"
        }, 
        {
         "id":100,
         "type":"tile"
        }, 
        {
         "id":101,
         "type":"tile"
        }, 
        {
         "id":102,
         "type":"tile"
        }, 
        {
         "id":103,
         "type":"tile"
        }, 
        {
         "id":104,
         "type":"tile"
        }, 
        {
         "id":105,
         "type":"tile"
        }, 
        {
         "id":106,
         "type":"tile"
        }, 
        {
         "id":107,
         "type":"tile"
        }, 
        {
         "id":108,
         "type":"tile"
        }, 
        {
         "id":109,
         "type":"tile"
        }, 
        {
         "id":110,
         "type":"tile"
        }, 
        {
         "id":111,
         "type":"tile"
        }, 
        {
         "id":112,
         "type":"tile"
        }, 
        {
         "id":113,
         "type":"tile"
        }, 
        {
         "id":114,
         "type":"tile"
        }, 
        {
         "id":115,
         "type":"tile"
        }, 
        {
         "id":116,
         "type":"tile"
        }, 
        {
         "id":117,
         "type":"tile"
        }, 
        {
         "id":118,
         "type":"tile"
        }, 
        {
         "id":119,
         "type":"tile"
        }, 
        {
         "id":120,
         "type":"tile"
        }, 
        {
         "id":121,
         "type":"tile"
        }, 
        {
         "id":122,
         "type":"tile"
        }, 
        {
         "id":123,
         "type":"tile"
        }, 
        {
         "id":124,
         "type":"tile"
        }, 
        {
         "id":125,
         "type":"tile"
        }, 
        {
         "id":126,
         "type":"tile"
        }, 
        {
         "id":127,
         "type":"tile"
        }, 
        {
         "id":128,
         "type":"tile"
        }, 
        {
         "id":129,
         "type":"tile"
        }, 
        {
         "id":130,
         "type":"tile"
        }, 
        {
         "id":131,
         "type":"tile"
        }, 
        {
         "id":132,
         "type":"tile"
        }, 
        {
         "id":133,
         "type":"tile"
        }, 
        {
         "id":134,
         "type":"tile"
        }, 
        {
         "id":135,
         "type":"tile"
        }, 
        {
         "id":136,
         "type":"tile"
        }, 
        {
         "id":137,
         "type":"tile"
        }, 
        {
         "id":138,
         "type":"tile"
        }, 
        {
         "id":139,
         "type":"tile"
        }, 
        {
         "id":140,
         "type":"tile"
        }, 
        {
         "id":141,
         "type":"tile"
        }, 
        {
         "id":142,
         "type":"tile"
        }, 
        {
         "id":143,
         "type":"tile"
        }, 
        {
         "id":144,
         "type":"tile"
        }, 
        {
         "id":145,
         "type":"tile"
        }, 
        {
         "id":146,
         "type":"tile"
        }, 
        {
         "id":147,
         "type":"tile"
        }, 
        {
         "id":148,
         "type":"tile"
        }, 
        {
         "id":149,
         "type":"tile"
        }, 
        {
         "id":150,
         "type":"tile"
        }, 
        {
         "id":151,
         "type":"tile"
        }, 
        {
         "id":152,
         "type":"tile"
        }, 
        {
         "id":153,
         "type":"tile"
        }, 
        {
         "id":154,
         "type":"tile"
        }, 
        {
         "id":155,
         "type":"tile"
        }, 
        {
         "id":156,
         "type":"tile"
        }, 
        {
         "id":157,
         "type":"tile"
        }, 
        {
         "id":158,
         "type":"tile"
        }, 
        {
         "id":159,
         "type":"tile"
        }, 
        {
         "id":160,
         "type":"tile"
        }, 
        {
         "id":161,
         "type":"tile"
        }, 
        {
         "id":162,
         "type":"tile"
        }, 
        {
         "id":163,
         "type":"tile"
        }, 
        {
         "id":164,
         "type":"tile"
        }, 
        {
         "id":165,
         "type":"tile"
        }, 
        {
         "id":166,
         "type":"tile"
        }, 
        {
         "id":167,
         "type":"tile"
        }, 
        {
         "id":168,
         "type":"tile"
        }, 
        {
         "id":169,
         "type":"tile"
        }, 
        {
         "id":170,
         "type":"tile"
        }, 
        {
         "id":171,
         "type":"tile"
        }, 
        {
         "id":172,
         "type":"tile"
        }, 
        {
         "id":173,
         "type":"tile"
        }, 
        {
         "id":174,
         "type":"tile"
        }, 
        {
         "id":175,
         "type":"tile"
        }, 
        {
         "id":176,
         "type":"tile"
        }, 
        {
         "id":177,
         "type":"tile"
        }, 
        {
         "id":178,
         "type":"tile"
        }, 
        {
         "id":179,
         "type":"tile"
        }, 
        {
         "id":180,
         "type":"tile"
        }, 
        {
         "id":181,
         "type":"tile"
        }, 
        {
         "id":182,
         "properties":[
                {
                 "name":"boss_lvl",
                 "type":"int",
                 "value":99
                }],
         "type":"tile"
        }, 
        {
         "id":183,
         "properties":[
                {
                 "name":"boss_lvl",
                 "type":"int",
                 "value":99
                }],
         "type":"tile"
        }, 
        {
         "id":184,
         "properties":[
                {
                 "name":"boss_lvl",
                 "type":"int",
                 "value":99
                }],
         "type":"tile"
        }, 
        {
         "id":185,
         "properties":[
                {
                 "name":"boss_lvl",
                 "type":"int",
                 "value":99
                }],
         "type":"tile"
        }, 
        {
         "id":186,
         "properties":[
                {
                 "name":"boss_lvl",
                 "type":"int",
                 "value":99
                }],
         "type":"tile"
        }, 
        {
         "id":187,
         "properties":[
                {
                 "name":"boss_lvl",
                 "type":"int",
                 "value":99
                }],
         "type":"tile"
        }, 
        {
         "id":188,
         "type":"tile"
        }, 
        {
         "id":189,
         "type":"tile"
        }, 
        {
         "id":190,
         "type":"tile"
        }, 
        {
         "id":191,
         "type":"tile"
        }, 
        {
         "id":192,
         "type":"tile"
        }, 
        {
         "id":193,
         "type":"tile"
        }, 
        {
         "id":194,
         "type":"tile"
        }, 
        {
         "id":195,
         "type":"tile"
        }, 
        {
         "id":196,
         "type":"tile"
        }, 
        {
         "id":197,
         "type":"tile"
        }, 
        {
         "id":198,
         "properties":[
                {
                 "name":"boss_lvl",
                 "type":"int",
                 "value":99
                }],
         "type":"tile"
        }, 
        {
         "id":199,
         "properties":[
                {
                 "name":"boss_lvl",
                 "type":"int",
                 "value":99
                }],
         "type":"tile"
        }, 
        {
         "id":200,
         "properties":[
                {
                 "name":"boss_lvl",
                 "type":"int",
                 "value":99
                }],
         "type":"tile"
        }, 
        {
         "id":201,
         "properties":[
                {
                 "name":"boss_lvl",
                 "type":"int",
                 "value":99
                }],
         "type":"tile"
        }, 
        {
         "id":202,
         "properties":[
                {
                 "name":"boss_lvl",
                 "type":"int",
                 "value":99
                }],
         "type":"tile"
        }, 
        {
         "id":203,
         "properties":[
                {
                 "name":"boss_lvl",
                 "type":"int",
                 "value":99
                }],
         "type":"tile"
        }, 
        {
         "id":204,
         "type":"tile"
        }, 
        {
         "id":205,
         "type":"tile"
        }, 
        {
         "id":206,
         "type":"tile"
        }, 
        {
         "id":207,
         "type":"tile"
        }, 
        {
         "id":208,
         "type":"tile"
        }, 
        {
         "id":209,
         "type":"tile"
        }, 
        {
         "id":210,
         "type":"tile"
        }, 
        {
         "id":211,
         "type":"tile"
        }, 
        {
         "id":212,
         "type":"tile"
        }, 
        {
         "id":213,
         "type":"tile"
        }, 
        {
         "id":214,
         "type":"tile"
        }, 
        {
         "id":215,
         "type":"tile"
        }, 
        {
         "id":216,
         "type":"tile"
        }, 
        {
         "id":217,
         "type":"tile"
        }, 
        {
         "id":218,
         "type":"tile"
        }, 
        {
         "id":219,
         "type":"tile"
        }, 
        {
         "id":220,
         "type":"tile"
        }, 
        {
         "id":221,
         "type":"tile"
        }, 
        {
         "id":222,
         "type":"tile"
        }, 
        {
         "id":223,
         "type":"tile"
        }, 
        {
         "id":224,
         "type":"tile"
        }, 
        {
         "id":225,
         "type":"tile"
        }, 
        {
         "id":226,
         "type":"tile"
        }, 
        {
         "id":227,
         "type":"tile"
        }, 
        {
         "id":228,
         "type":"tile"
        }, 
        {
         "id":229,
         "type":"tile"
        }, 
        {
         "id":230,
         "type":"tile"
        }, 
        {
         "id":231,
         "type":"tile"
        }, 
        {
         "id":232,
         "type":"tile"
        }, 
        {
         "id":233,
         "type":"tile"
        }, 
        {
         "id":234,
         "type":"tile"
        }, 
        {
         "id":235,
         "type":"tile"
        }, 
        {
         "id":236,
         "type":"tile"
        }, 
        {
         "id":237,
         "type":"tile"
        }, 
        {
         "id":238,
         "type":"tile"
        }, 
        {
         "id":239,
         "type":"tile"
        }, 
        {
         "id":240,
         "type":"tile"
        }, 
        {
         "id":241,
         "type":"tile"
        }, 
        {
         "id":242,
         "type":"tile"
        }, 
        {
         "id":243,
         "type":"tile"
        }, 
        {
         "id":244,
         "type":"tile"
        }, 
        {
         "id":245,
         "type":"tile"
        }, 
        {
         "id":246,
         "type":"tile"
        }, 
        {
         "id":247,
         "type":"tile"
        }, 
        {
         "id":248,
         "type":"tile"
        }, 
        {
         "id":249,
         "type":"tile"
        }, 
        {
         "id":250,
         "type":"tile"
        }, 
        {
         "id":251,
         "type":"tile"
        }, 
        {
         "id":252,
         "type":"tile"
        }, 
        {
         "id":253,
         "type":"tile"
        }, 
        {
         "id":254,
         "type":"tile"
        }, 
        {
         "id":255,
         "type":"tile"
        }],
 "tilewidth":16,
 "type":"tileset",
 "version":1.2
}